barbara/__init__.py
barbara/_utils.py
barbara/client.py
barbara/models.py
barbara/nodes.py
barbara/workloads.py
barbara_sdk-1.2.2.dist-info/METADATA
barbara_sdk-1.2.2.dist-info/WHEEL
barbara_sdk-1.2.2.dist-info/top_level.txt
barbara_sdk-1.2.2.dist-info/RECORD
